django_state_choice_field/__init__.py
django_state_choice_field/exceptions.py
django_state_choice_field/fields.py
django_state_choice_field/utils.py
django_state_choice_field/tests/__init__.py
django_state_choice_field/tests/models.py
django_state_choice_field/tests/test_module.py
django_state_choice_field/tests/test_settings.py
django_state_choice_field-0.0.1.dist-info/LICENSE
django_state_choice_field-0.0.1.dist-info/METADATA
django_state_choice_field-0.0.1.dist-info/WHEEL
django_state_choice_field-0.0.1.dist-info/top_level.txt
django_state_choice_field-0.0.1.dist-info/RECORD
