Metadata-Version: 2.1
Name: django-state-choice-field
Version: 0.0.1
Summary: A Django enum field
Home-page: https://github.com/themrinalsinha/django_state_choice_field
Author: Mrinal Sinha
Author-email: me@mrinal.xyz
Keywords: django_state_choice_field
Classifier: Environment :: Web Environment
Classifier: Framework :: Django
Classifier: Intended Audience :: Developers
Classifier: Programming Language :: Python :: 3.9
Classifier: Programming Language :: Python :: 3.10
Classifier: Programming Language :: Python :: 3.11
Classifier: Programming Language :: Python :: 3.12
Requires-Python: >=3.6, <4
License-File: LICENSE
Requires-Dist: Django >=3.2
